pybundestag/__init__.py
pybundestag/__main__.py
pybundestag/downloader/__init__.py
pybundestag/downloader/speechloader.py
pybundestag/parser/__init__.py
pybundestag/parser/mdbparser.py
pybundestag/parser/speechparser.py
pybundestag-0.0.21.dist-info/LICENSE
pybundestag-0.0.21.dist-info/METADATA
pybundestag-0.0.21.dist-info/WHEEL
pybundestag-0.0.21.dist-info/entry_points.txt
pybundestag-0.0.21.dist-info/top_level.txt
pybundestag-0.0.21.dist-info/RECORD
