Metadata-Version: 2.1
Name: pybundestag
Version: 0.0.21
Summary: Package to parse Bundestag data
Home-page: https://github.com/Jhruzik/pybundestag
Author: Joshua Hruzik
Author-email: joshua.hruzik@gmail.com
License: UNKNOWN
Platform: UNKNOWN
Classifier: Programming Language :: Python :: 3
Classifier: License :: OSI Approved :: MIT License
Classifier: Operating System :: OS Independent
Classifier: Development Status :: 3 - Alpha
Classifier: Environment :: Console
Classifier: Intended Audience :: Science/Research
Classifier: Topic :: Text Processing
Requires-Dist: pandas
Requires-Dist: bs4
Requires-Dist: lxml
